[
{"index":"LAESA","dataset":"Synthetic","category":"HFI","num_pivots":3,"num_centers_path":null,"query_type":"MRQ","selectivity":0.020000,"radius":2740.211800,"k":null,"compdists":5529.610000,"time_ms":0.245130,"n_queries":100,"run_id":1},
{"index":"LAESA","dataset":"Synthetic","category":"HFI","num_pivots":3,"num_centers_path":null,"query_type":"MRQ","selectivity":0.040000,"radius":3243.577200,"k":null,"compdists":8158.040000,"time_ms":0.253120,"n_queries":100,"run_id":1},
{"index":"LAESA","dataset":"Synthetic","category":"HFI","num_pivots":3,"num_centers_path":null,"query_type":"MRQ","selectivity":0.080000,"radius":3863.875200,"k":null,"compdists":11706.800000,"time_ms":0.301100,"n_queries":100,"run_id":1},
{"index":"LAESA","dataset":"Synthetic","category":"HFI","num_pivots":3,"num_centers_path":null,"query_type":"MRQ","selectivity":0.160000,"radius":4638.709600,"k":null,"compdists":16151.230000,"time_ms":0.355560,"n_queries":100,"run_id":1},
{"index":"LAESA","dataset":"Synthetic","category":"HFI","num_pivots":3,"num_centers_path":null,"query_type":"MRQ","selectivity":0.320000,"radius":5640.400400,"k":null,"compdists":21209.480000,"time_ms":0.348770,"n_queries":100,"run_id":1},
{"index":"LAESA","dataset":"Synthetic","category":"HFI","num_pivots":3,"num_centers_path":null,"query_type":"MkNN","selectivity":null,"radius":null,"k":5,"compdists":2037.080000,"time_ms":2.152690,"n_queries":100,"run_id":1},
{"index":"LAESA","dataset":"Synthetic","category":"HFI","num_pivots":3,"num_centers_path":null,"query_type":"MkNN","selectivity":null,"radius":null,"k":10,"compdists":2098.140000,"time_ms":2.097590,"n_queries":100,"run_id":1},
{"index":"LAESA","dataset":"Synthetic","category":"HFI","num_pivots":3,"num_centers_path":null,"query_type":"MkNN","selectivity":null,"radius":null,"k":20,"compdists":2196.420000,"time_ms":2.085200,"n_queries":100,"run_id":1},
{"index":"LAESA","dataset":"Synthetic","category":"HFI","num_pivots":3,"num_centers_path":null,"query_type":"MkNN","selectivity":null,"radius":null,"k":50,"compdists":2423.700000,"time_ms":2.151120,"n_queries":100,"run_id":1},
{"index":"LAESA","dataset":"Synthetic","category":"HFI","num_pivots":3,"num_centers_path":null,"query_type":"MkNN","selectivity":null,"radius":null,"k":100,"compdists":2733.140000,"time_ms":2.122340,"n_queries":100,"run_id":1},
{"index":"LAESA","dataset":"Synthetic","category":"HFI","num_pivots":5,"num_centers_path":null,"query_type":"MRQ","selectivity":0.020000,"radius":2740.211800,"k":null,"compdists":1986.300000,"time_ms":0.239270,"n_queries":100,"run_id":1},
{"index":"LAESA","dataset":"Synthetic","category":"HFI","num_pivots":5,"num_centers_path":null,"query_type":"MRQ","selectivity":0.040000,"radius":3243.577200,"k":null,"compdists":3809.440000,"time_ms":0.273890,"n_queries":100,"run_id":1},
{"index":"LAESA","dataset":"Synthetic","category":"HFI","num_pivots":5,"num_centers_path":null,"query_type":"MRQ","selectivity":0.080000,"radius":3863.875200,"k":null,"compdists":7018.520000,"time_ms":0.306060,"n_queries":100,"run_id":1},
{"index":"LAESA","dataset":"Synthetic","category":"HFI","num_pivots":5,"num_centers_path":null,"query_type":"MRQ","selectivity":0.160000,"radius":4638.709600,"k":null,"compdists":12110.320000,"time_ms":0.357170,"n_queries":100,"run_id":1},
{"index":"LAESA","dataset":"Synthetic","category":"HFI","num_pivots":5,"num_centers_path":null,"query_type":"MRQ","selectivity":0.320000,"radius":5640.400400,"k":null,"compdists":18762.810000,"time_ms":0.384510,"n_queries":100,"run_id":1},
{"index":"LAESA","dataset":"Synthetic","category":"HFI","num_pivots":5,"num_centers_path":null,"query_type":"MkNN","selectivity":null,"radius":null,"k":5,"compdists":1011.180000,"time_ms":2.180510,"n_queries":100,"run_id":1},
{"index":"LAESA","dataset":"Synthetic","category":"HFI","num_pivots":5,"num_centers_path":null,"query_type":"MkNN","selectivity":null,"radius":null,"k":10,"compdists":1095.910000,"time_ms":2.122310,"n_queries":100,"run_id":1},
{"index":"LAESA","dataset":"Synthetic","category":"HFI","num_pivots":5,"num_centers_path":null,"query_type":"MkNN","selectivity":null,"radius":null,"k":20,"compdists":1206.690000,"time_ms":2.154300,"n_queries":100,"run_id":1},
{"index":"LAESA","dataset":"Synthetic","category":"HFI","num_pivots":5,"num_centers_path":null,"query_type":"MkNN","selectivity":null,"radius":null,"k":50,"compdists":1425.000000,"time_ms":2.171340,"n_queries":100,"run_id":1},
{"index":"LAESA","dataset":"Synthetic","category":"HFI","num_pivots":5,"num_centers_path":null,"query_type":"MkNN","selectivity":null,"radius":null,"k":100,"compdists":1718.500000,"time_ms":2.186650,"n_queries":100,"run_id":1},
{"index":"LAESA","dataset":"Synthetic","category":"HFI","num_pivots":10,"num_centers_path":null,"query_type":"MRQ","selectivity":0.020000,"radius":2740.211800,"k":null,"compdists":177.310000,"time_ms":0.297380,"n_queries":100,"run_id":1},
{"index":"LAESA","dataset":"Synthetic","category":"HFI","num_pivots":10,"num_centers_path":null,"query_type":"MRQ","selectivity":0.040000,"radius":3243.577200,"k":null,"compdists":722.270000,"time_ms":0.331860,"n_queries":100,"run_id":1},
{"index":"LAESA","dataset":"Synthetic","category":"HFI","num_pivots":10,"num_centers_path":null,"query_type":"MRQ","selectivity":0.080000,"radius":3863.875200,"k":null,"compdists":2358.740000,"time_ms":0.350540,"n_queries":100,"run_id":1},
{"index":"LAESA","dataset":"Synthetic","category":"HFI","num_pivots":10,"num_centers_path":null,"query_type":"MRQ","selectivity":0.160000,"radius":4638.709600,"k":null,"compdists":6436.790000,"time_ms":0.421460,"n_queries":100,"run_id":1},
{"index":"LAESA","dataset":"Synthetic","category":"HFI","num_pivots":10,"num_centers_path":null,"query_type":"MRQ","selectivity":0.320000,"radius":5640.400400,"k":null,"compdists":14384.570000,"time_ms":0.498340,"n_queries":100,"run_id":1},
{"index":"LAESA","dataset":"Synthetic","category":"HFI","num_pivots":10,"num_centers_path":null,"query_type":"MkNN","selectivity":null,"radius":null,"k":5,"compdists":718.270000,"time_ms":2.266620,"n_queries":100,"run_id":1},
{"index":"LAESA","dataset":"Synthetic","category":"HFI","num_pivots":10,"num_centers_path":null,"query_type":"MkNN","selectivity":null,"radius":null,"k":10,"compdists":797.860000,"time_ms":2.318590,"n_queries":100,"run_id":1},
{"index":"LAESA","dataset":"Synthetic","category":"HFI","num_pivots":10,"num_centers_path":null,"query_type":"MkNN","selectivity":null,"radius":null,"k":20,"compdists":887.500000,"time_ms":2.337290,"n_queries":100,"run_id":1},
{"index":"LAESA","dataset":"Synthetic","category":"HFI","num_pivots":10,"num_centers_path":null,"query_type":"MkNN","selectivity":null,"radius":null,"k":50,"compdists":1057.250000,"time_ms":2.314460,"n_queries":100,"run_id":1},
{"index":"LAESA","dataset":"Synthetic","category":"HFI","num_pivots":10,"num_centers_path":null,"query_type":"MkNN","selectivity":null,"radius":null,"k":100,"compdists":1265.870000,"time_ms":2.368530,"n_queries":100,"run_id":1},
{"index":"LAESA","dataset":"Synthetic","category":"HFI","num_pivots":15,"num_centers_path":null,"query_type":"MRQ","selectivity":0.020000,"radius":2740.211800,"k":null,"compdists":31.870000,"time_ms":0.424350,"n_queries":100,"run_id":1},
{"index":"LAESA","dataset":"Synthetic","category":"HFI","num_pivots":15,"num_centers_path":null,"query_type":"MRQ","selectivity":0.040000,"radius":3243.577200,"k":null,"compdists":180.550000,"time_ms":0.443760,"n_queries":100,"run_id":1},
{"index":"LAESA","dataset":"Synthetic","category":"HFI","num_pivots":15,"num_centers_path":null,"query_type":"MRQ","selectivity":0.080000,"radius":3863.875200,"k":null,"compdists":934.690000,"time_ms":0.437350,"n_queries":100,"run_id":1},
{"index":"LAESA","dataset":"Synthetic","category":"HFI","num_pivots":15,"num_centers_path":null,"query_type":"MRQ","selectivity":0.160000,"radius":4638.709600,"k":null,"compdists":3714.120000,"time_ms":0.504120,"n_queries":100,"run_id":1},
{"index":"LAESA","dataset":"Synthetic","category":"HFI","num_pivots":15,"num_centers_path":null,"query_type":"MRQ","selectivity":0.320000,"radius":5640.400400,"k":null,"compdists":11043.110000,"time_ms":0.624190,"n_queries":100,"run_id":1},
{"index":"LAESA","dataset":"Synthetic","category":"HFI","num_pivots":15,"num_centers_path":null,"query_type":"MkNN","selectivity":null,"radius":null,"k":5,"compdists":285.710000,"time_ms":2.585230,"n_queries":100,"run_id":1},
{"index":"LAESA","dataset":"Synthetic","category":"HFI","num_pivots":15,"num_centers_path":null,"query_type":"MkNN","selectivity":null,"radius":null,"k":10,"compdists":401.980000,"time_ms":2.533070,"n_queries":100,"run_id":1},
{"index":"LAESA","dataset":"Synthetic","category":"HFI","num_pivots":15,"num_centers_path":null,"query_type":"MkNN","selectivity":null,"radius":null,"k":20,"compdists":469.650000,"time_ms":2.503100,"n_queries":100,"run_id":1},
{"index":"LAESA","dataset":"Synthetic","category":"HFI","num_pivots":15,"num_centers_path":null,"query_type":"MkNN","selectivity":null,"radius":null,"k":50,"compdists":612.690000,"time_ms":2.591520,"n_queries":100,"run_id":1},
{"index":"LAESA","dataset":"Synthetic","category":"HFI","num_pivots":15,"num_centers_path":null,"query_type":"MkNN","selectivity":null,"radius":null,"k":100,"compdists":790.730000,"time_ms":2.585550,"n_queries":100,"run_id":1},
{"index":"LAESA","dataset":"Synthetic","category":"HFI","num_pivots":20,"num_centers_path":null,"query_type":"MRQ","selectivity":0.020000,"radius":2740.211800,"k":null,"compdists":21.800000,"time_ms":0.528250,"n_queries":100,"run_id":1},
{"index":"LAESA","dataset":"Synthetic","category":"HFI","num_pivots":20,"num_centers_path":null,"query_type":"MRQ","selectivity":0.040000,"radius":3243.577200,"k":null,"compdists":68.720000,"time_ms":0.520980,"n_queries":100,"run_id":1},
{"index":"LAESA","dataset":"Synthetic","category":"HFI","num_pivots":20,"num_centers_path":null,"query_type":"MRQ","selectivity":0.080000,"radius":3863.875200,"k":null,"compdists":466.970000,"time_ms":0.575840,"n_queries":100,"run_id":1},
{"index":"LAESA","dataset":"Synthetic","category":"HFI","num_pivots":20,"num_centers_path":null,"query_type":"MRQ","selectivity":0.160000,"radius":4638.709600,"k":null,"compdists":2564.360000,"time_ms":0.610030,"n_queries":100,"run_id":1},
{"index":"LAESA","dataset":"Synthetic","category":"HFI","num_pivots":20,"num_centers_path":null,"query_type":"MRQ","selectivity":0.320000,"radius":5640.400400,"k":null,"compdists":9629.180000,"time_ms":0.717880,"n_queries":100,"run_id":1},
{"index":"LAESA","dataset":"Synthetic","category":"HFI","num_pivots":20,"num_centers_path":null,"query_type":"MkNN","selectivity":null,"radius":null,"k":5,"compdists":92.240000,"time_ms":2.705630,"n_queries":100,"run_id":1},
{"index":"LAESA","dataset":"Synthetic","category":"HFI","num_pivots":20,"num_centers_path":null,"query_type":"MkNN","selectivity":null,"radius":null,"k":10,"compdists":200.130000,"time_ms":2.781680,"n_queries":100,"run_id":1},
{"index":"LAESA","dataset":"Synthetic","category":"HFI","num_pivots":20,"num_centers_path":null,"query_type":"MkNN","selectivity":null,"radius":null,"k":20,"compdists":263.890000,"time_ms":2.766440,"n_queries":100,"run_id":1},
{"index":"LAESA","dataset":"Synthetic","category":"HFI","num_pivots":20,"num_centers_path":null,"query_type":"MkNN","selectivity":null,"radius":null,"k":50,"compdists":381.780000,"time_ms":2.791210,"n_queries":100,"run_id":1},
{"index":"LAESA","dataset":"Synthetic","category":"HFI","num_pivots":20,"num_centers_path":null,"query_type":"MkNN","selectivity":null,"radius":null,"k":100,"compdists":535.160000,"time_ms":2.715060,"n_queries":100,"run_id":1}
]
