[
{"index":"BST","dataset":"LA","category":"CP","num_pivots":0,"num_centers_path":3,"arity":null,"query_type":"MRQ","selectivity":0.020000,"radius":31.334346,"k":null,"compdists":1394.240000,"time_ms":0.017430,"n_queries":100,"run_id":1},
{"index":"BST","dataset":"LA","category":"CP","num_pivots":0,"num_centers_path":3,"arity":null,"query_type":"MRQ","selectivity":0.040000,"radius":51.125681,"k":null,"compdists":1414.600000,"time_ms":0.017560,"n_queries":100,"run_id":1},
{"index":"BST","dataset":"LA","category":"CP","num_pivots":0,"num_centers_path":3,"arity":null,"query_type":"MRQ","selectivity":0.080000,"radius":79.666485,"k":null,"compdists":1450.860000,"time_ms":0.018570,"n_queries":100,"run_id":1},
{"index":"BST","dataset":"LA","category":"CP","num_pivots":0,"num_centers_path":3,"arity":null,"query_type":"MRQ","selectivity":0.160000,"radius":120.043472,"k":null,"compdists":1493.550000,"time_ms":0.020120,"n_queries":100,"run_id":1},
{"index":"BST","dataset":"LA","category":"CP","num_pivots":0,"num_centers_path":3,"arity":null,"query_type":"MRQ","selectivity":0.320000,"radius":188.422684,"k":null,"compdists":1528.630000,"time_ms":0.021310,"n_queries":100,"run_id":1},
{"index":"BST","dataset":"LA","category":"CP","num_pivots":0,"num_centers_path":3,"arity":null,"query_type":"MkNN","selectivity":null,"radius":null,"k":5,"compdists":1624.220000,"time_ms":0.027190,"n_queries":100,"run_id":1},
{"index":"BST","dataset":"LA","category":"CP","num_pivots":0,"num_centers_path":3,"arity":null,"query_type":"MkNN","selectivity":null,"radius":null,"k":10,"compdists":1625.370000,"time_ms":0.033150,"n_queries":100,"run_id":1},
{"index":"BST","dataset":"LA","category":"CP","num_pivots":0,"num_centers_path":3,"arity":null,"query_type":"MkNN","selectivity":null,"radius":null,"k":20,"compdists":1626.520000,"time_ms":0.041470,"n_queries":100,"run_id":1},
{"index":"BST","dataset":"LA","category":"CP","num_pivots":0,"num_centers_path":3,"arity":null,"query_type":"MkNN","selectivity":null,"radius":null,"k":50,"compdists":1633.070000,"time_ms":0.067530,"n_queries":100,"run_id":1},
{"index":"BST","dataset":"LA","category":"CP","num_pivots":0,"num_centers_path":3,"arity":null,"query_type":"MkNN","selectivity":null,"radius":null,"k":100,"compdists":1645.320000,"time_ms":0.100250,"n_queries":100,"run_id":1},
{"index":"BST","dataset":"LA","category":"CP","num_pivots":0,"num_centers_path":5,"arity":null,"query_type":"MRQ","selectivity":0.020000,"radius":31.334346,"k":null,"compdists":1014.070000,"time_ms":0.013200,"n_queries":100,"run_id":1},
{"index":"BST","dataset":"LA","category":"CP","num_pivots":0,"num_centers_path":5,"arity":null,"query_type":"MRQ","selectivity":0.040000,"radius":51.125681,"k":null,"compdists":1076.010000,"time_ms":0.014400,"n_queries":100,"run_id":1},
{"index":"BST","dataset":"LA","category":"CP","num_pivots":0,"num_centers_path":5,"arity":null,"query_type":"MRQ","selectivity":0.080000,"radius":79.666485,"k":null,"compdists":1177.370000,"time_ms":0.015900,"n_queries":100,"run_id":1},
{"index":"BST","dataset":"LA","category":"CP","num_pivots":0,"num_centers_path":5,"arity":null,"query_type":"MRQ","selectivity":0.160000,"radius":120.043472,"k":null,"compdists":1252.780000,"time_ms":0.017560,"n_queries":100,"run_id":1},
{"index":"BST","dataset":"LA","category":"CP","num_pivots":0,"num_centers_path":5,"arity":null,"query_type":"MRQ","selectivity":0.320000,"radius":188.422684,"k":null,"compdists":1444.500000,"time_ms":0.020810,"n_queries":100,"run_id":1},
{"index":"BST","dataset":"LA","category":"CP","num_pivots":0,"num_centers_path":5,"arity":null,"query_type":"MkNN","selectivity":null,"radius":null,"k":5,"compdists":1292.800000,"time_ms":0.022400,"n_queries":100,"run_id":1},
{"index":"BST","dataset":"LA","category":"CP","num_pivots":0,"num_centers_path":5,"arity":null,"query_type":"MkNN","selectivity":null,"radius":null,"k":10,"compdists":1309.350000,"time_ms":0.029480,"n_queries":100,"run_id":1},
{"index":"BST","dataset":"LA","category":"CP","num_pivots":0,"num_centers_path":5,"arity":null,"query_type":"MkNN","selectivity":null,"radius":null,"k":20,"compdists":1330.250000,"time_ms":0.038910,"n_queries":100,"run_id":1},
{"index":"BST","dataset":"LA","category":"CP","num_pivots":0,"num_centers_path":5,"arity":null,"query_type":"MkNN","selectivity":null,"radius":null,"k":50,"compdists":1343.220000,"time_ms":0.069320,"n_queries":100,"run_id":1},
{"index":"BST","dataset":"LA","category":"CP","num_pivots":0,"num_centers_path":5,"arity":null,"query_type":"MkNN","selectivity":null,"radius":null,"k":100,"compdists":1373.010000,"time_ms":0.099190,"n_queries":100,"run_id":1},
{"index":"BST","dataset":"LA","category":"CP","num_pivots":0,"num_centers_path":10,"arity":null,"query_type":"MRQ","selectivity":0.020000,"radius":31.334346,"k":null,"compdists":251.810000,"time_ms":0.007120,"n_queries":100,"run_id":1},
{"index":"BST","dataset":"LA","category":"CP","num_pivots":0,"num_centers_path":10,"arity":null,"query_type":"MRQ","selectivity":0.040000,"radius":51.125681,"k":null,"compdists":333.440000,"time_ms":0.007610,"n_queries":100,"run_id":1},
{"index":"BST","dataset":"LA","category":"CP","num_pivots":0,"num_centers_path":10,"arity":null,"query_type":"MRQ","selectivity":0.080000,"radius":79.666485,"k":null,"compdists":453.100000,"time_ms":0.009170,"n_queries":100,"run_id":1},
{"index":"BST","dataset":"LA","category":"CP","num_pivots":0,"num_centers_path":10,"arity":null,"query_type":"MRQ","selectivity":0.160000,"radius":120.043472,"k":null,"compdists":632.300000,"time_ms":0.013020,"n_queries":100,"run_id":1},
{"index":"BST","dataset":"LA","category":"CP","num_pivots":0,"num_centers_path":10,"arity":null,"query_type":"MRQ","selectivity":0.320000,"radius":188.422684,"k":null,"compdists":1003.830000,"time_ms":0.017990,"n_queries":100,"run_id":1},
{"index":"BST","dataset":"LA","category":"CP","num_pivots":0,"num_centers_path":10,"arity":null,"query_type":"MkNN","selectivity":null,"radius":null,"k":5,"compdists":348.420000,"time_ms":0.011480,"n_queries":100,"run_id":1},
{"index":"BST","dataset":"LA","category":"CP","num_pivots":0,"num_centers_path":10,"arity":null,"query_type":"MkNN","selectivity":null,"radius":null,"k":10,"compdists":605.420000,"time_ms":0.021050,"n_queries":100,"run_id":1},
{"index":"BST","dataset":"LA","category":"CP","num_pivots":0,"num_centers_path":10,"arity":null,"query_type":"MkNN","selectivity":null,"radius":null,"k":20,"compdists":677.650000,"time_ms":0.034190,"n_queries":100,"run_id":1},
{"index":"BST","dataset":"LA","category":"CP","num_pivots":0,"num_centers_path":10,"arity":null,"query_type":"MkNN","selectivity":null,"radius":null,"k":50,"compdists":728.420000,"time_ms":0.063460,"n_queries":100,"run_id":1},
{"index":"BST","dataset":"LA","category":"CP","num_pivots":0,"num_centers_path":10,"arity":null,"query_type":"MkNN","selectivity":null,"radius":null,"k":100,"compdists":809.800000,"time_ms":0.090290,"n_queries":100,"run_id":1},
{"index":"BST","dataset":"LA","category":"CP","num_pivots":0,"num_centers_path":15,"arity":null,"query_type":"MRQ","selectivity":0.020000,"radius":31.334346,"k":null,"compdists":162.130000,"time_ms":0.005870,"n_queries":100,"run_id":1},
{"index":"BST","dataset":"LA","category":"CP","num_pivots":0,"num_centers_path":15,"arity":null,"query_type":"MRQ","selectivity":0.040000,"radius":51.125681,"k":null,"compdists":240.360000,"time_ms":0.006400,"n_queries":100,"run_id":1},
{"index":"BST","dataset":"LA","category":"CP","num_pivots":0,"num_centers_path":15,"arity":null,"query_type":"MRQ","selectivity":0.080000,"radius":79.666485,"k":null,"compdists":356.660000,"time_ms":0.008690,"n_queries":100,"run_id":1},
{"index":"BST","dataset":"LA","category":"CP","num_pivots":0,"num_centers_path":15,"arity":null,"query_type":"MRQ","selectivity":0.160000,"radius":120.043472,"k":null,"compdists":547.820000,"time_ms":0.012080,"n_queries":100,"run_id":1},
{"index":"BST","dataset":"LA","category":"CP","num_pivots":0,"num_centers_path":15,"arity":null,"query_type":"MRQ","selectivity":0.320000,"radius":188.422684,"k":null,"compdists":900.490000,"time_ms":0.018950,"n_queries":100,"run_id":1},
{"index":"BST","dataset":"LA","category":"CP","num_pivots":0,"num_centers_path":15,"arity":null,"query_type":"MkNN","selectivity":null,"radius":null,"k":5,"compdists":184.760000,"time_ms":0.010300,"n_queries":100,"run_id":1},
{"index":"BST","dataset":"LA","category":"CP","num_pivots":0,"num_centers_path":15,"arity":null,"query_type":"MkNN","selectivity":null,"radius":null,"k":10,"compdists":248.360000,"time_ms":0.018340,"n_queries":100,"run_id":1},
{"index":"BST","dataset":"LA","category":"CP","num_pivots":0,"num_centers_path":15,"arity":null,"query_type":"MkNN","selectivity":null,"radius":null,"k":20,"compdists":301.770000,"time_ms":0.027320,"n_queries":100,"run_id":1},
{"index":"BST","dataset":"LA","category":"CP","num_pivots":0,"num_centers_path":15,"arity":null,"query_type":"MkNN","selectivity":null,"radius":null,"k":50,"compdists":418.450000,"time_ms":0.048750,"n_queries":100,"run_id":1},
{"index":"BST","dataset":"LA","category":"CP","num_pivots":0,"num_centers_path":15,"arity":null,"query_type":"MkNN","selectivity":null,"radius":null,"k":100,"compdists":554.100000,"time_ms":0.075390,"n_queries":100,"run_id":1},
{"index":"BST","dataset":"LA","category":"CP","num_pivots":0,"num_centers_path":20,"arity":null,"query_type":"MRQ","selectivity":0.020000,"radius":31.334346,"k":null,"compdists":155.140000,"time_ms":0.004900,"n_queries":100,"run_id":1},
{"index":"BST","dataset":"LA","category":"CP","num_pivots":0,"num_centers_path":20,"arity":null,"query_type":"MRQ","selectivity":0.040000,"radius":51.125681,"k":null,"compdists":230.460000,"time_ms":0.006470,"n_queries":100,"run_id":1},
{"index":"BST","dataset":"LA","category":"CP","num_pivots":0,"num_centers_path":20,"arity":null,"query_type":"MRQ","selectivity":0.080000,"radius":79.666485,"k":null,"compdists":344.990000,"time_ms":0.009570,"n_queries":100,"run_id":1},
{"index":"BST","dataset":"LA","category":"CP","num_pivots":0,"num_centers_path":20,"arity":null,"query_type":"MRQ","selectivity":0.160000,"radius":120.043472,"k":null,"compdists":540.630000,"time_ms":0.012540,"n_queries":100,"run_id":1},
{"index":"BST","dataset":"LA","category":"CP","num_pivots":0,"num_centers_path":20,"arity":null,"query_type":"MRQ","selectivity":0.320000,"radius":188.422684,"k":null,"compdists":894.920000,"time_ms":0.017710,"n_queries":100,"run_id":1},
{"index":"BST","dataset":"LA","category":"CP","num_pivots":0,"num_centers_path":20,"arity":null,"query_type":"MkNN","selectivity":null,"radius":null,"k":5,"compdists":170.660000,"time_ms":0.010090,"n_queries":100,"run_id":1},
{"index":"BST","dataset":"LA","category":"CP","num_pivots":0,"num_centers_path":20,"arity":null,"query_type":"MkNN","selectivity":null,"radius":null,"k":10,"compdists":263.310000,"time_ms":0.019700,"n_queries":100,"run_id":1},
{"index":"BST","dataset":"LA","category":"CP","num_pivots":0,"num_centers_path":20,"arity":null,"query_type":"MkNN","selectivity":null,"radius":null,"k":20,"compdists":366.320000,"time_ms":0.035130,"n_queries":100,"run_id":1},
{"index":"BST","dataset":"LA","category":"CP","num_pivots":0,"num_centers_path":20,"arity":null,"query_type":"MkNN","selectivity":null,"radius":null,"k":50,"compdists":515.100000,"time_ms":0.059950,"n_queries":100,"run_id":1},
{"index":"BST","dataset":"LA","category":"CP","num_pivots":0,"num_centers_path":20,"arity":null,"query_type":"MkNN","selectivity":null,"radius":null,"k":100,"compdists":660.020000,"time_ms":0.090250,"n_queries":100,"run_id":1}
]
