[
{"index":"SPBTree","dataset":"Color","category":"SPB","num_pivots":5,"query_type":"MRQ","selectivity":0.020000,"radius":3729.367400,"k":null,"compdists":1212.250000,"time_ms":1.807540,"pages":78.400000,"n_queries":100,"run_id":1},
{"index":"SPBTree","dataset":"Color","category":"SPB","num_pivots":5,"query_type":"MRQ","selectivity":0.040000,"radius":4110.865200,"k":null,"compdists":1336.830000,"time_ms":1.867540,"pages":78.400000,"n_queries":100,"run_id":1},
{"index":"SPBTree","dataset":"Color","category":"SPB","num_pivots":5,"query_type":"MRQ","selectivity":0.080000,"radius":4519.708800,"k":null,"compdists":1453.340000,"time_ms":1.892860,"pages":78.400000,"n_queries":100,"run_id":1},
{"index":"SPBTree","dataset":"Color","category":"SPB","num_pivots":5,"query_type":"MRQ","selectivity":0.160000,"radius":5018.284400,"k":null,"compdists":1570.630000,"time_ms":1.941500,"pages":78.400000,"n_queries":100,"run_id":1},
{"index":"SPBTree","dataset":"Color","category":"SPB","num_pivots":5,"query_type":"MRQ","selectivity":0.320000,"radius":5702.488400,"k":null,"compdists":1697.820000,"time_ms":2.109710,"pages":78.400000,"n_queries":100,"run_id":1},
{"index":"SPBTree","dataset":"Color","category":"SPB","num_pivots":5,"query_type":"MkNN","selectivity":null,"radius":null,"k":5,"compdists":6.000000,"time_ms":0.042050,"pages":10.000000,"n_queries":100,"run_id":1},
{"index":"SPBTree","dataset":"Color","category":"SPB","num_pivots":5,"query_type":"MkNN","selectivity":null,"radius":null,"k":10,"compdists":6.000000,"time_ms":0.042050,"pages":10.000000,"n_queries":100,"run_id":1},
{"index":"SPBTree","dataset":"Color","category":"SPB","num_pivots":5,"query_type":"MkNN","selectivity":null,"radius":null,"k":20,"compdists":6.000000,"time_ms":0.042150,"pages":10.000000,"n_queries":100,"run_id":1},
{"index":"SPBTree","dataset":"Color","category":"SPB","num_pivots":5,"query_type":"MkNN","selectivity":null,"radius":null,"k":50,"compdists":6.000000,"time_ms":0.042060,"pages":10.000000,"n_queries":100,"run_id":1},
{"index":"SPBTree","dataset":"Color","category":"SPB","num_pivots":5,"query_type":"MkNN","selectivity":null,"radius":null,"k":100,"compdists":6.000000,"time_ms":0.041870,"pages":10.000000,"n_queries":100,"run_id":1}
]
